daon
