Metadata-Version: 1.0
Name: daon
Version: 0.1.7.1
Summary: Daon Korean Analyzer
Home-page: http://github.com/rasoio/daon-python
Author: rasoio
Author-email: rasoio@naver.com
License: MIT
Platform: UNKNOWN
